[
    {
        "name": "Rude",
        "url": "https://www.kkbox.com/tw/tc/song/H-hb5QmqCJ6qxjJxMM",
        "artist": "MAGIC! (魔幻樂團)"
    },
    {
        "name": "Playa Del Inglés",
        "url": "https://www.kkbox.com/tw/tc/song/CnPV5BiJUCArqzrQFw",
        "artist": "Quevedo, Myke Towers"
    },
    {
        "name": "No Lie",
        "url": "https://www.kkbox.com/tw/tc/song/XaT-IqXriLniLykPmu",
        "artist": "Sean Paul (尚保羅)"
    },
    {
        "name": "Go Down Deh (feat. Shaggy and Sean Paul)",
        "url": "https://www.kkbox.com/tw/tc/song/-p9F6kwxzoZVou5EA6",
        "artist": "Spice"
    },
    {
        "name": "Healing House",
        "url": "https://www.kkbox.com/tw/tc/song/5Zhxc6VBsZjzsL-Gwh",
        "artist": "Phum Viphurit"
    },
    {
        "name": "Sobrio",
        "url": "https://www.kkbox.com/tw/tc/song/KnF8LX_sKmKv7_jjXK",
        "artist": "Maluma"
    },
    {
        "name": "Sin Pijama",
        "url": "https://www.kkbox.com/tw/tc/song/CtPMW6e1USEGa6oith",
        "artist": "Becky G, Natti Natasha"
    },
    {
        "name": "Todo De Ti",
        "url": "https://www.kkbox.com/tw/tc/song/D-dpIpPGldMinD4g8V",
        "artist": "Rauw Alejandro"
    },
    {
        "name": "Unforgettable",
        "url": "https://www.kkbox.com/tw/tc/song/Glg4ALXpylVNHSLYdP",
        "artist": "French Montana"
    },
    {
        "name": "Mad Love",
        "url": "https://www.kkbox.com/tw/tc/song/KmgEE_FYR1boNFsDQW",
        "artist": "Sean Paul, David Guetta"
    },
    {
        "name": "Sweet & Sour",
        "url": "https://www.kkbox.com/tw/tc/song/-neHCWAoz-JyhdtPR8",
        "artist": "Jawsh 685"
    },
    {
        "name": "Cheerleader",
        "url": "https://www.kkbox.com/tw/tc/song/X-KzpYgL-uxSigZplI",
        "artist": "OMI"
    },
    {
        "name": "Hawái",
        "url": "https://www.kkbox.com/tw/tc/song/9ZZHx_ous_ZpGZmndg",
        "artist": "Maluma"
    },
    {
        "name": "El Amante",
        "url": "https://www.kkbox.com/tw/tc/song/GnOkevkWJNIVLcaLtm",
        "artist": "Nicky Jam"
    },
    {
        "name": "Stressed Out",
        "url": "https://www.kkbox.com/tw/tc/song/Kt9cZALlIXgP2QNE33",
        "artist": "Irv Shotti"
    },
    {
        "name": "Me Gusta",
        "url": "https://www.kkbox.com/tw/tc/song/PZfEAKAFfVd6iSVaHa",
        "artist": "Shakira (夏奇拉)"
    },
    {
        "name": "PUNTO 40",
        "url": "https://www.kkbox.com/tw/tc/song/Oml8zlRdTsIBdy4-kj",
        "artist": "Rauw Alejandro, Baby Rasta"
    },
    {
        "name": "Don Don",
        "url": "https://www.kkbox.com/tw/tc/song/CtEFDOS1USEGb_TYHt",
        "artist": "Daddy Yankee, Anuel AA, Kendo Kaponi"
    },
    {
        "name": "Limbo",
        "url": "https://www.kkbox.com/tw/tc/song/5-R-ueA-i4L5qy1JhJ",
        "artist": "Daddy Yankee (洋基老爹)"
    },
    {
        "name": "BOMBÓN",
        "url": "https://www.kkbox.com/tw/tc/song/4nPqpB5o3TYuoWVFSe",
        "artist": "Daddy Yankee (洋基老爹)"
    },
    {
        "name": "(I Can't Help) Falling In Love With You",
        "url": "https://www.kkbox.com/tw/tc/song/0pnYXKF1MinpXt1C4s",
        "artist": "Various Artists"
    },
    {
        "name": "Ten Cane Row",
        "url": "https://www.kkbox.com/tw/tc/song/0pn-buGFMinpVvq4Zn",
        "artist": "Protoje"
    },
    {
        "name": "Iko Iko (My Bestie)",
        "url": "https://www.kkbox.com/tw/tc/song/0lrUkHgXs1XUda2Qrh",
        "artist": "Justin Wellington"
    },
    {
        "name": "Ram Pam Pam",
        "url": "https://www.kkbox.com/tw/tc/song/8qY-P_EcYrrZOMpr9X",
        "artist": "Natti Natasha, Becky G"
    },
    {
        "name": "Lonely Hours",
        "url": "https://www.kkbox.com/tw/tc/song/9acTC4dt1jmuJpx-L-",
        "artist": "Soaky Siren"
    },
    {
        "name": "So So So",
        "url": "https://www.kkbox.com/tw/tc/song/_XBYB_Ne0EWg-stN0o",
        "artist": "ChiBaba MrConfahm"
    },
    {
        "name": "Sangria Wine",
        "url": "https://www.kkbox.com/tw/tc/song/SlZ7YW_7Ox5G2_Cd8i",
        "artist": "Pharrell Williams, Camila Cabello"
    },
    {
        "name": "Sweat (A La La La La Long)",
        "url": "https://www.kkbox.com/tw/tc/song/OoFM6c8632AqbhNBx2",
        "artist": "Inner Circle (內心圓合唱團)"
    },
    {
        "name": "LEJOS DEL CIELO",
        "url": "https://www.kkbox.com/tw/tc/song/SsvQj3K_DXYxZf6adm",
        "artist": "Rauw Alejandro"
    },
    {
        "name": "Calma",
        "url": "https://www.kkbox.com/tw/tc/song/GnTfMdiWJNIVKWJkpg",
        "artist": "Pedro Capó, Farruko"
    },
    {
        "name": "Gban Gban",
        "url": "https://www.kkbox.com/tw/tc/song/-qMMQPPALDIxCms4cm",
        "artist": "ChiBaba MrConfahm"
    },
    {
        "name": "Hasta el Amanecer",
        "url": "https://www.kkbox.com/tw/tc/song/HaGz9kGFE8K3YTi3_O",
        "artist": "Nicky Jam"
    },
    {
        "name": "Important Property",
        "url": "https://www.kkbox.com/tw/tc/song/CqvUbeISUh-7_ELZRb",
        "artist": "ChiBaba MrConfahm"
    },
    {
        "name": "When I Wake Up",
        "url": "https://www.kkbox.com/tw/tc/song/KkArsApD5hrtAyVH08",
        "artist": "ChiBaba MrConfahm"
    },
    {
        "name": "Approach Her",
        "url": "https://www.kkbox.com/tw/tc/song/-qztsPPALDIxB8JMcK",
        "artist": "ChiBaba MrConfahm"
    },
    {
        "name": "Unu Bia",
        "url": "https://www.kkbox.com/tw/tc/song/_aUa0WwwAvqjZs78Jh",
        "artist": "ChiBaba MrConfahm"
    },
    {
        "name": "If You Want To Make It",
        "url": "https://www.kkbox.com/tw/tc/song/5Y2ocd4HhYuu0SHtjL",
        "artist": "ChiBaba MrConfahm"
    },
    {
        "name": "Banana (feat. Shaggy) - DJ FLe - Minisiren Remix",
        "url": "https://www.kkbox.com/tw/tc/song/StaaLb6i4xyDIQKQND",
        "artist": "Conkarah"
    },
    {
        "name": "Laxed (Siren Beat)",
        "url": "https://www.kkbox.com/tw/tc/song/Kr9867ZH6Il0A8b5U0",
        "artist": "Jawsh 685"
    },
    {
        "name": "No Worries",
        "url": "https://www.kkbox.com/tw/tc/song/8r6gWtUE59bDSLb29J",
        "artist": "ChiBaba MrConfahm"
    },
    {
        "name": "Victorious",
        "url": "https://www.kkbox.com/tw/tc/song/OkWbfFb3wySdKLxu7K",
        "artist": "ChiBaba MrConfahm"
    },
    {
        "name": "Beautiful Girls",
        "url": "https://www.kkbox.com/tw/tc/song/CpM56ZZ_XVWGvCjVkd",
        "artist": "Various Artists"
    },
    {
        "name": "Te deseo",
        "url": "https://www.kkbox.com/tw/tc/song/D-Dgn1PmldMimIuE1_",
        "artist": "AC"
    },
    {
        "name": "I Can See Clearly Now",
        "url": "https://www.kkbox.com/tw/tc/song/P-Nhi_F2hnTeOLcQvX",
        "artist": "Johnny Nash (強尼納許)"
    },
    {
        "name": "No Woman No Cry",
        "url": "https://www.kkbox.com/tw/tc/song/-tSc-APJZ3RLvLbYGT",
        "artist": "Bob Marley (巴布馬利)"
    },
    {
        "name": "Writing on the Wall",
        "url": "https://www.kkbox.com/tw/tc/song/T-Ymq5ou-xXCVBaiNx",
        "artist": "French Montana"
    },
    {
        "name": "El Perdón",
        "url": "https://www.kkbox.com/tw/tc/song/KoSFUhdxP2VFsJ0W8k",
        "artist": "Nicky Jam"
    },
    {
        "name": "One Day",
        "url": "https://www.kkbox.com/tw/tc/song/WkGQqZFpPowcmN6NKI",
        "artist": "Matisyahu (瑪堤斯亞胡)"
    },
    {
        "name": "Buenos Aires",
        "url": "https://www.kkbox.com/tw/tc/song/GmSy1zeT7q4F41b5En",
        "artist": "Cuba Torres"
    },
    {
        "name": "Bad Boys (Theme from COPS)",
        "url": "https://www.kkbox.com/tw/tc/song/4swkuhtDOGRFil0Qja",
        "artist": "Inner Circle (內心圓合唱團)"
    },
    {
        "name": "Be Where Your Feet Are",
        "url": "https://www.kkbox.com/tw/tc/song/4sEVpJnzOGRFiEXWXr",
        "artist": "Jason Mraz (傑森‧瑪耶茲)"
    },
    {
        "name": "Where Did I Go Wrong",
        "url": "https://www.kkbox.com/tw/tc/song/8o0X2hsAlULSBv4hUr",
        "artist": "UB40"
    },
    {
        "name": "Red Red Wine - 7” Version",
        "url": "https://www.kkbox.com/tw/tc/song/CpiAB8XvXVWGsD-62G",
        "artist": "UB40"
    },
    {
        "name": "Felices los 4",
        "url": "https://www.kkbox.com/tw/tc/song/4s880loTOGRFi0SOlm",
        "artist": "Maluma"
    },
    {
        "name": "Pull Up",
        "url": "https://www.kkbox.com/tw/tc/song/4nr8eO543TYuqGTuvX",
        "artist": "Koffee"
    },
    {
        "name": "Cuba",
        "url": "https://www.kkbox.com/tw/tc/song/CsoxrV6N3ZiY3YmINo",
        "artist": "AC"
    }
]